{"id": "toilet", "children": [{"id": "bottle", "children": [{"id": "person", "children": [{"id": "car", "children": [{"id": "bicycle"}, {"id": "motorcycle"}, {"id": "bus"}, {"id": "truck"}, {"id": "traffic light"}]}, {"id": "bench"}, {"id": "backpack", "children": [{"id": "suitcase"}, {"id": "skis", "children": [{"id": "snowboard"}]}]}, {"id": "handbag", "children": [{"id": "umbrella"}]}, {"id": "sports ball", "children": [{"id": "baseball bat"}, {"id": "baseball glove"}, {"id": "tennis racket"}]}]}, {"id": "wine glass"}, {"id": "cup", "children": [{"id": "sandwich", "children": [{"id": "hot dog"}]}, {"id": "cake"}, {"id": "laptop"}, {"id": "cell phone"}]}, {"id": "fork", "children": [{"id": "broccoli"}, {"id": "carrot"}]}, {"id": "knife"}, {"id": "spoon"}, {"id": "bowl", "children": [{"id": "apple", "children": [{"id": "banana"}]}, {"id": "orange"}]}, {"id": "pizza"}, {"id": "chair", "children": [{"id": "couch"}, {"id": "remote"}]}, {"id": "potted plant"}, {"id": "dining table"}, {"id": "tv", "children": [{"id": "mouse"}, {"id": "keyboard"}]}, {"id": "microwave"}, {"id": "oven"}, {"id": "refrigerator"}, {"id": "book", "children": [{"id": "bed"}]}, {"id": "vase"}]}, {"id": "sink"}, {"id": "toothbrush"}]}